[
	{
		"symbol": "?createPacket@MinecraftPackets@@SA?AV?$shared_ptr@VPacket@@@std@@W4MinecraftPacketIds@@@Z",
		"signature": "48 89 5C 24 ? 48 89 6C 24 ? 48 89 74 24 ? 57 48 83 EC ? 48 8B F9 48 89 4C 24 ? 33 ED 81 FA"
	},
	{
		"symbol": "?getTimeOfDay@Dimension@@QEAAMHM@Z",
		"signature": "44 8B C2 B8 F1 19 76 05 F7 EA"
	},
	{
		"symbol": "?renderLevel@LevelRenderer@@QEAAXAEAVScreenContext@@AEBVFrameRenderObject@@@Z",
		"signature": "48 8B C4 48 89 58 ? 55 56 57 41 54 41 55 41 56 41 57 48 8D A8 ? ? ? ? 48 81 EC ? ? ? ? 0F 29 70 ? 0F 29 78 ? 44 0F 29 40 ? 44 0F 29 48 ? 48 8B 05 ? ? ? ? 48 33 C4 48 89 85 ? ? ? ? 4D 8B E8 4C 8B E2 4C 8B F9"
	},
	{
		"symbol": "?render@ScreenView@@QEAAXAEAVUIRenderContext@@@Z",
		"signature": "48 89 5C 24 ? 55 56 57 41 54 41 55 41 56 41 57 48 8D AC 24 ? ? ? ? 48 81 EC ? ? ? ? 0F 29 BC 24 ? ? ? ? 48 8B 05 ? ? ? ? 48 33 C4 48 89 85 ? ? ? ? 4C 8B FA"
	},
	{
		"symbol": "?submit@RendererContextD3D11@d3d11@bgfx@@QEAAXPEAVFrame@@AEAVClearQuad@@AEAVTextVideoMemBlitter@@@Z",
		"signature": "48 8B C4 55 53 56 57 41 54 41 55 41 56 41 57 48 81 EC ? ? ? ? 0F 29 70 ? 0F 29 78 ? 44 0F 29 40 ? 44 0F 29 88 ? ? ? ? 48 8D A8"
	},
	{
		"symbol": "?submit@RendererContextD3D12@d3d12@bgfx@@QEAAXPEAVFrame@@AEAVClearQuad@@AEAVTextVideoMemBlitter@@@Z",
		"signature": "48 89 5C 24 ? 55 56 57 41 54 41 55 41 56 41 57 48 8D AC 24 ? ? ? ? B8 ? ? ? ? E8 ? ? ? ? 48 2B E0 0F 29 B4 24 ? ? ? ? 0F 29 BC 24 ? ? ? ? 44 0F 29 84 24 ? ? ? ? 48 8B 05 ? ? ? ? 48 33 C4 48 89 85 ? ? ? ? 4C 89 4C 24"
	},
	{
		"symbol": "?isDeviceRemoved@RendererContextD3D11@d3d11@bgfx@@QEAA_NXZ",
		"signature": "83 B9 ? ? ? ? ? 0F 94 C0 C3 CC CC CC CC CC 40 53 48 83 EC ? 48 8B 05"
	},
	{
		"symbol": "?isDeviceRemoved@RendererContextD3D12@d3d12@bgfx@@QEAA_NXZ",
		"signature": "83 B9 ? ? ? ? ? 0F 94 C0 C3 CC CC CC CC CC B2"
	},
	{
		"symbol": "?_update@MinecraftGame@@QEAAXXZ",
		"signature": "E8 ? ? ? ? 48 8B 8E ? ? ? ? BA ? ? ? ? E8 ? ? ? ? 48 8B BE",
		"deref": 1
	},
	{
		"symbol": "?grabCursor@ClientInstance@@QEAAXXZ",
		"signature": "40 53 48 83 EC ? 48 8B 01 48 8B D9 48 8B 80 ? ? ? ? FF 15 ? ? ? ? 84 C0 74 ? 48 8B 8B ? ? ? ? 48 8B 01 48 8B 80 ? ? ? ? 48 83 C4 ? 5B 48 FF 25 ? ? ? ? 48 83 C4 ? 5B C3 40 53"
	},
	{
		"symbol": "?releaseCursor@ClientInstance@@QEAAXXZ",
		"signature": "40 53 48 83 EC ? 48 8B 01 48 8B D9 48 8B 80 ? ? ? ? FF 15 ? ? ? ? 84 C0 74 ? 48 8B 8B ? ? ? ? 48 8B 01 48 8B 80 ? ? ? ? 48 83 C4 ? 5B 48 FF 25 ? ? ? ? 48 83 C4 ? 5B C3 48 89 5C 24"
	},
	{
		"symbol": "?onDeviceLost@MinecraftGame@@QEAAXXZ",
		"signature": "48 89 5C 24 ? 48 89 6C 24 ? 48 89 74 24 ? 57 48 83 EC ? 48 8B F1 33 ED 89 6C 24"
	},
	{
		"symbol": "?displayClientMessage@GuiData@@QEAAXAEBV?$basic_string@DU?$char_traits@D@std@@V?$allocator@D@2@@std@@AEBV?$optional@V?$basic_string@DU?$char_traits@D@std@@V?$allocator@D@2@@std@@@3@_N@Z",
		"signature": "40 55 53 56 57 41 56 48 8D AC 24 ? ? ? ? 48 81 EC ? ? ? ? 48 8B 05 ? ? ? ? 48 33 C4 48 89 85 ? ? ? ? 41 0F B6 ? 49 8B D8"
	},
	{
		"symbol": "?GetAveragePing@RakPeer@RakNet@@QEAAHVAddressOrGUID@2@@Z",
		"signature": "48 8B C4 55 48 8D 6C 24 ? 48 81 EC ? ? ? ? 0F 10 4A ? 4C 8B 1A 4C 3B 1D ? ? ? ? 0F 10 42 ? 48 89 58 ? 48 8B D9 0F 10 52 ? 0F 10 5A ? 0F 10 62 ? 0F 10 6A ? 0F 29 70 ? 0F 10 72 ? 0F 29 78 ? 0F B7 82 ? ? ? ? 0F 10 BA ? ? ? ? 66 89 45 ? 0F B7 82 ? ? ? ? 66 89 45 ? 0F 11 4C 24 ? 74 ? 44 8B 49"
	}
]